client/__init__.py
client/client.py
client/client/__init__.py
client/client/add_contact.py
client/client/database.py
client/client/del_contact.py
client/client/main_window.py
client/client/main_window_conv.py
client/client/start_dialog.py
client/client/transport.py
client/common/__init__.py
client/common/decorators.py
client/common/descriptors.py
client/common/errors.py
client/common/metaclass.py
client/common/utils.py
client/common/variables.py
client/logs/__init__.py
client/logs/app_log_config.py
client/logs/client_log_config.py
client/logs/server_log_config.py
client_messanger-1.2.dist-info/METADATA
client_messanger-1.2.dist-info/WHEEL
client_messanger-1.2.dist-info/top_level.txt
client_messanger-1.2.dist-info/RECORD
