Metadata-Version: 2.1
Name: client-messanger
Version: 1.2
Summary: Client part
Home-page: UNKNOWN
Author: Pleshakov Sergey
Author-email: red13_74@mail.ru
License: UNKNOWN
Platform: UNKNOWN
